README.md
setup.py
distributions/ClassLicenseGeneratorDist.py
distributions/DateGeneratorDist.py
distributions/NameGeneratorDist.py
distributions/SourcesLoaderDist.py
distributions/__init__.py
driver_license_gen.egg-info/PKG-INFO
driver_license_gen.egg-info/SOURCES.txt
driver_license_gen.egg-info/dependency_links.txt
driver_license_gen.egg-info/not-zip-safe
driver_license_gen.egg-info/top_level.txt