Metadata-Version: 1.0
Name: driver-license-gen
Version: 1.0
Summary: U.S. driver license generator
Home-page: UNKNOWN
Author: Roggeo
Author-email: geovanirog@gmail.com
License: UNKNOWN
Platform: UNKNOWN
